odt2sphinx/__init__.py
odt2sphinx/odt2sphinx.py
odt2sphinx-0.3.0.dist-info/DESCRIPTION.rst
odt2sphinx-0.3.0.dist-info/METADATA
odt2sphinx-0.3.0.dist-info/RECORD
odt2sphinx-0.3.0.dist-info/WHEEL
odt2sphinx-0.3.0.dist-info/entry_points.txt
odt2sphinx-0.3.0.dist-info/metadata.json
odt2sphinx-0.3.0.dist-info/top_level.txt
