Metadata-Version: 2.0
Name: odt2sphinx
Version: 0.3.0
Summary: An OpenDocument to sphinx converter.
Home-page: https://bitbucket.org/cdevienne/odt2sphinx
Author: Christophe de Vienne
Author-email: <cdevienne@gmail.com>
License: UNKNOWN
Platform: UNKNOWN
Classifier: Development Status :: 4 - Beta
Classifier: Environment :: Console
Classifier: License :: OSI Approved :: Python Software Foundation License
Classifier: Programming Language :: Python :: 2.5
Classifier: Programming Language :: Python :: 2.6
Classifier: Programming Language :: Python :: 2.7
Classifier: Programming Language :: Python :: 3
Classifier: Topic :: Documentation
Classifier: Topic :: Software Development :: Documentation
Requires-Dist: Pillow
Requires-Dist: six
